elsa_menu/__init__.py
elsa_menu/abstract_class.py
elsa_menu/color.py
elsa_menu/instance_object.py
elsa_menu/keyboard_input.py
elsa_menu/menu.py
elsa_menu/menu_element.py
elsa_menu/menu_object.py
ElsaMenu-1.0.1.dist-info/LICENSE
ElsaMenu-1.0.1.dist-info/METADATA
ElsaMenu-1.0.1.dist-info/WHEEL
ElsaMenu-1.0.1.dist-info/top_level.txt
ElsaMenu-1.0.1.dist-info/RECORD
