Metadata-Version: 2.1
Name: ElsaMenu
Version: 1.0.1
Summary: Easy menu with python3
Home-page: https://gitlab.com/Elsalamander1/elsamenu
Author: Elsalamander
Author-email: edilinguanotto@gmail.com
Classifier: Programming Language :: Python :: 3.8
Classifier: License :: OSI Approved :: MIT License
Classifier: Operating System :: OS Independent
Requires-Python: >=3.8
License-File: LICENSE
